pagelabels/__init__.py
pagelabels/__main__.py
pagelabels/pagelabels.py
pagelabels/pagelabelscheme.py
pagelabels-1.2.1.dist-info/LICENSE
pagelabels-1.2.1.dist-info/METADATA
pagelabels-1.2.1.dist-info/WHEEL
pagelabels-1.2.1.dist-info/top_level.txt
pagelabels-1.2.1.dist-info/RECORD
