Metadata-Version: 2.1
Name: pagelabels
Version: 1.2.1
Summary: Python library to manipulate PDF page numbers and labels.
Home-page: https://github.com/lovasoa/pagelabels-py
Author: Ophir LOJKINE
Author-email: pere.jobs@gmail.com
Keywords: pdf,page labels,page numbers,title page
Classifier: Development Status :: 5 - Production/Stable
Classifier: Environment :: Console
Classifier: Operating System :: OS Independent
Classifier: Intended Audience :: End Users/Desktop
Classifier: Programming Language :: Python
Classifier: Programming Language :: Python :: 3.5
Classifier: Programming Language :: Python :: 3.6
Classifier: Topic :: Text Processing
Classifier: Topic :: Utilities
License-File: LICENSE
Requires-Dist: pdfrw
